valesearch/__init__.py
valesearch/cli.py
valesearch/main.py
valesearch/vale_search.py
valesearch/api/__init__.py
valesearch/api/routes.py
valesearch/api/schemas.py
valesearch/retrieval/__init__.py
valesearch/retrieval/bm25_search.py
valesearch/retrieval/fallback_integration.py
valesearch/retrieval/hybrid_engine.py
valesearch/retrieval/reranker.py
valesearch/retrieval/vector_search.py
valesearch/utils/__init__.py
valesearch/utils/logger.py
valesearch-0.1.0.dist-info/LICENSE
valesearch-0.1.0.dist-info/METADATA
valesearch-0.1.0.dist-info/WHEEL
valesearch-0.1.0.dist-info/entry_points.txt
valesearch-0.1.0.dist-info/top_level.txt
valesearch-0.1.0.dist-info/RECORD
