Metadata-Version: 2.1
Name: valesearch
Version: 0.1.0
Summary: Hybrid cached retrieval engine for RAG systems - Drag-and-drop performance boost
Home-page: https://github.com/zyaddj/vale_search
Author: Zyad Djouad
Author-email: Zyad Djouad <zyaddj@valesolutions.net>
License: MIT
Project-URL: Homepage, https://github.com/zyaddj/vale_search
Project-URL: Repository, https://github.com/zyaddj/vale_search
Project-URL: Documentation, https://github.com/zyaddj/vale_search#readme
Project-URL: Bug Tracker, https://github.com/zyaddj/vale_search/issues
Keywords: rag,retrieval,cache,ai,ml,nlp,search,hybrid,bm25,vector,semantic
Classifier: Development Status :: 4 - Beta
Classifier: Intended Audience :: Developers
Classifier: License :: OSI Approved :: MIT License
Classifier: Operating System :: OS Independent
Classifier: Programming Language :: Python :: 3
Classifier: Programming Language :: Python :: 3.8
Classifier: Programming Language :: Python :: 3.9
Classifier: Programming Language :: Python :: 3.10
Classifier: Programming Language :: Python :: 3.11
Classifier: Topic :: Software Development :: Libraries :: Python Modules
Classifier: Topic :: Scientific/Engineering :: Artificial Intelligence
Requires-Python: >=3.8
License-File: LICENSE
Requires-Dist: fastapi>=0.104.1
Requires-Dist: redis>=5.0.1
Requires-Dist: rank-bm25>=0.2.2
Requires-Dist: sentence-transformers>=2.2.2
Requires-Dist: numpy>=1.24.3
Requires-Dist: nltk>=3.8.1
Requires-Dist: pydantic>=2.4.2
Requires-Dist: httpx>=0.24.0
Requires-Dist: scikit-learn>=1.0.0
Requires-Dist: click>=8.0.0
Provides-Extra: dev
Requires-Dist: pytest>=7.0.0; extra == "dev"
Requires-Dist: pytest-asyncio>=0.21.0; extra == "dev"
Requires-Dist: black>=22.0.0; extra == "dev"
Requires-Dist: isort>=5.0.0; extra == "dev"
Requires-Dist: flake8>=5.0.0; extra == "dev"
Provides-Extra: gpu
Requires-Dist: faiss-gpu>=1.7.4; extra == "gpu"
Provides-Extra: server
Requires-Dist: uvicorn[standard]>=0.24.0; extra == "server"
